odoo9_addon_stock_lot_scrap-9.0.1.0.0-py2.7-nspkg.pth
odoo_addons/stock_lot_scrap/__openerp__.py
odoo_addons/stock_lot_scrap/__init__.py
odoo_addons/stock_lot_scrap/README.rst
odoo_addons/stock_lot_scrap/models/stock_scrap_lot.py
odoo_addons/stock_lot_scrap/models/__init__.py
odoo_addons/stock_lot_scrap/i18n/it.po
odoo_addons/stock_lot_scrap/i18n/es.po
odoo_addons/stock_lot_scrap/i18n/sl.po
odoo_addons/stock_lot_scrap/i18n/de.po
odoo_addons/stock_lot_scrap/i18n/fr.po
odoo_addons/stock_lot_scrap/tests/test_stock_lot_scrap.py
odoo_addons/stock_lot_scrap/tests/__init__.py
odoo_addons/stock_lot_scrap/static/description/icon.png
odoo9_addon_stock_lot_scrap-9.0.1.0.0.dist-info/top_level.txt
odoo9_addon_stock_lot_scrap-9.0.1.0.0.dist-info/WHEEL
odoo9_addon_stock_lot_scrap-9.0.1.0.0.dist-info/RECORD
odoo9_addon_stock_lot_scrap-9.0.1.0.0.dist-info/metadata.json
odoo9_addon_stock_lot_scrap-9.0.1.0.0.dist-info/DESCRIPTION.rst
odoo9_addon_stock_lot_scrap-9.0.1.0.0.dist-info/METADATA
odoo9_addon_stock_lot_scrap-9.0.1.0.0.dist-info/namespace_packages.txt
